setup.py
seawiki/__init__.py
seawiki/seawiki.py
seawiki.egg-info/PKG-INFO
seawiki.egg-info/SOURCES.txt
seawiki.egg-info/dependency_links.txt
seawiki.egg-info/requires.txt
seawiki.egg-info/top_level.txt
seawiki/drqa/__init__.py
seawiki/drqa/pipeline/__init__.py
seawiki/drqa/pipeline/drqa.py
seawiki/drqa/retriever/__init__.py
seawiki/drqa/retriever/doc_db.py
seawiki/drqa/retriever/elastic_doc_ranker.py
seawiki/drqa/retriever/tfidf_doc_ranker.py
seawiki/drqa/retriever/utils.py
seawiki/drqa/tokenizers/__init__.py
seawiki/drqa/tokenizers/corenlp_tokenizer.py
seawiki/drqa/tokenizers/regexp_tokenizer.py
seawiki/drqa/tokenizers/simple_tokenizer.py
seawiki/drqa/tokenizers/spacy_tokenizer.py
seawiki/drqa/tokenizers/tokenizer.py