Metadata-Version: 1.0
Name: seawiki
Version: 2019.10.25.1
Summary: Input a question, search wikipedia for the most similar documents
Home-page: https://github.com/DefuLi/Sea-Wiki
Author: defuli
Author-email: defuli.go@qq.com
License: MIT Licence
Platform: any
